neuropredict/__classify__.py
neuropredict/__init__.py
neuropredict/__regress__.py
neuropredict/_version.py
neuropredict/algorithms.py
neuropredict/base.py
neuropredict/classify.py
neuropredict/compare.py
neuropredict/config.py
neuropredict/datasets.py
neuropredict/freesurfer.py
neuropredict/io.py
neuropredict/regress.py
neuropredict/reports.py
neuropredict/results.py
neuropredict/utils.py
neuropredict/visualize.py
neuropredict/tests/_test_utils.py
neuropredict/tests/cmap_trials_conf_matrix.py
neuropredict/tests/debug.py
neuropredict/tests/est_time_per_pipeline_param.py
neuropredict/tests/example_datasets.py
neuropredict/tests/idempotent_fit.py
neuropredict/tests/make_vis.py
neuropredict/tests/matlib.ipynb
neuropredict/tests/np_test_utils.py
neuropredict/tests/test_AUC_calc.py
neuropredict/tests/test_CVResults_classes.py
neuropredict/tests/test_classify_workflow.py
neuropredict/tests/test_metrics.py
neuropredict/tests/test_missing_data.py
neuropredict/tests/test_multi_output.py
neuropredict/tests/test_new_pyradigm_format.py
neuropredict/tests/test_regress_workflow.py
neuropredict/tests/test_retrain_best_model_on_ALL_train_data.py
neuropredict/tests/test_rhst.py
neuropredict/tests/cmap_selection_trials/num_classes_2/cmap_sel_nc2_trial0.png
neuropredict/tests/cmap_selection_trials/num_classes_2/cmap_sel_nc2_trial1.png
neuropredict/tests/cmap_selection_trials/num_classes_2/cmap_sel_nc2_trial2.png
neuropredict/tests/cmap_selection_trials/num_classes_2/cmap_sel_nc2_trial3.png
neuropredict/tests/cmap_selection_trials/num_classes_2/cmap_sel_nc2_trial4.png
neuropredict/tests/cmap_selection_trials/num_classes_3/cmap_sel_nc3_trial0.png
neuropredict/tests/cmap_selection_trials/num_classes_3/cmap_sel_nc3_trial1.png
neuropredict/tests/cmap_selection_trials/num_classes_3/cmap_sel_nc3_trial2.png
neuropredict/tests/cmap_selection_trials/num_classes_3/cmap_sel_nc3_trial3.png
neuropredict/tests/cmap_selection_trials/num_classes_3/cmap_sel_nc3_trial4.png
neuropredict-0.6.3.dist-info/METADATA
neuropredict-0.6.3.dist-info/WHEEL
neuropredict-0.6.3.dist-info/entry_points.txt
neuropredict-0.6.3.dist-info/licenses/LICENSE
neuropredict-0.6.3.dist-info/RECORD
