Metadata-Version: 2.4
Name: neuropredict
Version: 0.6.3
Summary: easy and standardized predictive analysis for biomarkers, neuroimaging, and beyond
Project-URL: Homepage, https://github.com/raamana/neuropredict
Author-email: Pradeep Reddy Raamana <raamana@gmail.com>
License-Expression: Apache-2.0
License-File: LICENSE
Classifier: Intended Audience :: Science/Research
Classifier: Operating System :: MacOS
Classifier: Operating System :: Microsoft :: Windows
Classifier: Operating System :: POSIX
Classifier: Operating System :: Unix
Classifier: Programming Language :: Python
Classifier: Programming Language :: Python :: 3.11
Classifier: Topic :: Scientific/Engineering
Classifier: Topic :: Software Development
Requires-Python: >=3.7
Requires-Dist: confounds
Requires-Dist: matplotlib
Requires-Dist: nibabel
Requires-Dist: numpy
Requires-Dist: pyradigm>=0.6.dev1
Requires-Dist: scikit-learn
Requires-Dist: scipy
Requires-Dist: setuptools
